91life_ds_lib-1.0.0.dist-info/licenses/LICENSE
ninetyone_life_ds/__init__.py
ninetyone_life_ds/core/__init__.py
ninetyone_life_ds/core/config.py
ninetyone_life_ds/core/exceptions.py
ninetyone_life_ds/core/logger.py
ninetyone_life_ds/data/__init__.py
ninetyone_life_ds/data/explorer.py
ninetyone_life_ds/data/loader.py
ninetyone_life_ds/features/__init__.py
ninetyone_life_ds/features/preprocessor.py
ninetyone_life_ds/features/selector.py
ninetyone_life_ds/reports/__init__.py
ninetyone_life_ds/reports/generator.py
ninetyone_life_ds/visualization/__init__.py
ninetyone_life_ds/visualization/plotter.py
91life_ds_lib-1.0.0.dist-info/METADATA
91life_ds_lib-1.0.0.dist-info/WHEEL
91life_ds_lib-1.0.0.dist-info/entry_points.txt
91life_ds_lib-1.0.0.dist-info/top_level.txt
91life_ds_lib-1.0.0.dist-info/RECORD
