Metadata-Version: 2.4
Name: 91life-ds-lib
Version: 1.0.0
Summary: Professional Data Science Library for ML Engineers and Researchers
Author-email: Shpat Dobraj <shpatdobraj@91.life>
License: 91Life
Project-URL: Homepage, https://github.com/91life/91life-ds-lib
Project-URL: Documentation, https://91life-ds-lib.readthedocs.io/
Project-URL: Repository, https://github.com/91life/91life-ds-lib.git
Project-URL: Bug Tracker, https://github.com/91life/91life-ds-lib/issues
Project-URL: Source Code, https://github.com/91life/91life-ds-lib
Keywords: data-science,machine-learning,data-analysis,feature-selection,data-preprocessing
Classifier: Development Status :: 5 - Production/Stable
Classifier: Intended Audience :: Science/Research
Classifier: Intended Audience :: Developers
Classifier: License :: Other/Proprietary License
Classifier: Operating System :: OS Independent
Classifier: Programming Language :: Python :: 3
Classifier: Programming Language :: Python :: 3.8
Classifier: Programming Language :: Python :: 3.9
Classifier: Programming Language :: Python :: 3.10
Classifier: Programming Language :: Python :: 3.11
Classifier: Programming Language :: Python :: 3.12
Classifier: Topic :: Scientific/Engineering :: Artificial Intelligence
Classifier: Topic :: Scientific/Engineering :: Information Analysis
Classifier: Topic :: Software Development :: Libraries :: Python Modules
Requires-Python: >=3.8
License-File: LICENSE
Requires-Dist: pandas>=1.5.0
Requires-Dist: numpy>=1.21.0
Requires-Dist: scikit-learn>=1.1.0
Requires-Dist: matplotlib>=3.5.0
Requires-Dist: seaborn>=0.11.0
Requires-Dist: plotly>=5.10.0
Requires-Dist: scipy>=1.9.0
Requires-Dist: pydantic>=2.0.0
Requires-Dist: pydantic-settings>=2.1.0
Requires-Dist: tqdm>=4.64.0
Requires-Dist: psutil>=5.9.0
Requires-Dist: memory-profiler>=0.60.0
Requires-Dist: openpyxl>=3.0.0
Requires-Dist: pyarrow>=10.0.0
Requires-Dist: fastparquet>=0.8.0
Requires-Dist: aiofiles>=22.0.0
Requires-Dist: asyncio-throttle>=1.0.0
Requires-Dist: python-dotenv>=0.19.0
Requires-Dist: statsmodels>=0.13.0
Requires-Dist: imbalanced-learn>=0.9.0
Requires-Dist: kaleido>=0.2.1
Requires-Dist: jinja2>=3.1.0
Provides-Extra: dev
Requires-Dist: pytest>=7.0.0; extra == "dev"
Requires-Dist: pytest-cov>=4.0.0; extra == "dev"
Requires-Dist: pytest-asyncio>=0.21.0; extra == "dev"
Requires-Dist: black>=22.0.0; extra == "dev"
Requires-Dist: flake8>=5.0.0; extra == "dev"
Requires-Dist: mypy>=1.0.0; extra == "dev"
Requires-Dist: pre-commit>=2.20.0; extra == "dev"
Requires-Dist: bandit>=1.7.0; extra == "dev"
Requires-Dist: safety>=2.0.0; extra == "dev"
Provides-Extra: cloud
Requires-Dist: boto3>=1.26.0; extra == "cloud"
Requires-Dist: google-cloud-storage>=2.7.0; extra == "cloud"
Requires-Dist: minio>=7.1.0; extra == "cloud"
Requires-Dist: azure-storage-blob>=12.19.0; extra == "cloud"
Requires-Dist: azure-identity>=1.15.0; extra == "cloud"
Provides-Extra: profiling
Requires-Dist: ydata-profiling>=4.0.0; extra == "profiling"
Requires-Dist: sweetviz>=2.3.0; extra == "profiling"
Provides-Extra: all
Requires-Dist: 91life-ds-lib[cloud,dev,profiling]; extra == "all"
Dynamic: license-file
